ben_demo_package/__init__.py
ben_demo_package/demo_stats.py
ben_demo_package-0.4.0.dist-info/WHEEL
ben_demo_package-0.4.0.dist-info/entry_points.txt
ben_demo_package-0.4.0.dist-info/METADATA
ben_demo_package-0.4.0.dist-info/RECORD
