Metadata-Version: 2.3
Name: ben-demo-package
Version: 0.4.0
Summary: Add your description here
Author: Ben
Author-email: Ben <bennyp2494@gmail.com>
Requires-Dist: scipy>=1.13.1
Requires-Python: >=3.9
